.DS_Store
.gitignore
CHANGELOG
LICENSE
README.md
SchemaCombined903.xsd
__init__.py
setup.py
LitleSdkPython3.egg-info/PKG-INFO
LitleSdkPython3.egg-info/SOURCES.txt
LitleSdkPython3.egg-info/dependency_links.txt
LitleSdkPython3.egg-info/requires.txt
LitleSdkPython3.egg-info/top_level.txt
bin/postGeneration.py
litleSdkPython/Communications.py
litleSdkPython/Configuration.py
litleSdkPython/__init__.py
litleSdkPython/litleBatchRequest.py
litleSdkPython/litleBatchResponse.py
litleSdkPython/litleOnlineRequest.py
litleSdkPython/litleXmlFields.py
litleSdkPython/responseParser.py
litleSdkPythonTest/.gitignore
litleSdkPythonTest/setupConfig.py
litleSdkPythonTest/all/SetupTest.py
litleSdkPythonTest/all/TestAll.py
litleSdkPythonTest/certification/.gitignore
litleSdkPythonTest/certification/AllCertificationTests.py
litleSdkPythonTest/certification/TestCert1.py
litleSdkPythonTest/certification/TestCert2.py
litleSdkPythonTest/certification/TestCert3.py
litleSdkPythonTest/certification/TestCert4.py
litleSdkPythonTest/certification/TestCert5.py
litleSdkPythonTest/functional/.gitignore
litleSdkPythonTest/functional/AllFunctionalTests.py
litleSdkPythonTest/functional/TestAuth.py
litleSdkPythonTest/functional/TestAuthReversal.py
litleSdkPythonTest/functional/TestBatch.py
litleSdkPythonTest/functional/TestBatchTcp.py
litleSdkPythonTest/functional/TestCapture.py
litleSdkPythonTest/functional/TestCaptureGivenAuth.py
litleSdkPythonTest/functional/TestCredit.py
litleSdkPythonTest/functional/TestEcheckCredit.py
litleSdkPythonTest/functional/TestEcheckRedeposit.py
litleSdkPythonTest/functional/TestEcheckSale.py
litleSdkPythonTest/functional/TestEcheckVerification.py
litleSdkPythonTest/functional/TestEcheckVoid.py
litleSdkPythonTest/functional/TestForceCapture.py
litleSdkPythonTest/functional/TestSale.py
litleSdkPythonTest/functional/TestToken.py
litleSdkPythonTest/functional/TestUpdateCardValidationNumOnToken.py
litleSdkPythonTest/functional/TestUtf8.py
litleSdkPythonTest/runAllTestsAndSamples/RunAllTestsAndSamples.py
litleSdkPythonTest/unit/.gitignore
litleSdkPythonTest/unit/AllUnitTests.py
litleSdkPythonTest/unit/TestConfigOverride.py
litleSdkPythonTest/unit/TestCreateFromDom.py
